ll_ifc/__init__.py
linklabs_host_interface-1.5.1.dist-info/LICENSE.txt
linklabs_host_interface-1.5.1.dist-info/METADATA
linklabs_host_interface-1.5.1.dist-info/WHEEL
linklabs_host_interface-1.5.1.dist-info/top_level.txt
linklabs_host_interface-1.5.1.dist-info/RECORD
