Metadata-Version: 2.1
Name: linklabs-host-interface
Version: 1.5.1
Summary: Linklabs module interface
Home-page: https://www.link-labs.com
Author: Link Labs LLC
Author-email: support@link-labs.com
License: MIT
Keywords: link labs symphony conductor
Platform: UNKNOWN
Classifier: Development Status :: 4 - Beta
Classifier: Intended Audience :: Developers
Classifier: License :: OSI Approved :: MIT License
Classifier: Programming Language :: Python :: 2
Classifier: Programming Language :: Python :: 2.7
Classifier: Programming Language :: Python :: 3
Classifier: Programming Language :: Python :: 3.5
Requires-Dist: pyserial
